walle/__init__.py
walle/agent.py
walle/cache.py
walle/config.py
walle/core.py
walle/graph_query.py
walle/prompt_builder.py
walle/suggest/__init__.py
walle/suggest/suggest_friends.py
walle_ai-0.1.12.dist-info/licenses/LICENSE
walle_ai-0.1.12.dist-info/METADATA
walle_ai-0.1.12.dist-info/WHEEL
walle_ai-0.1.12.dist-info/top_level.txt
walle_ai-0.1.12.dist-info/RECORD
