Metadata-Version: 2.4
Name: walle_ai
Version: 0.1.12
Summary: WALLE. AI using Neo4j + OpenAI
Author-email: Enosh Lartey <larteyenosh@gmail.com>
License: MIT
Project-URL: Homepage, https://github.com/enoshlartey/walle_ai
Classifier: Programming Language :: Python :: 3
Classifier: License :: OSI Approved :: MIT License
Classifier: Operating System :: OS Independent
Requires-Python: >=3.10
License-File: LICENSE
Requires-Dist: openai
Requires-Dist: neo4j
Requires-Dist: python-dotenv
Requires-Dist: pandas
Requires-Dist: redis
Requires-Dist: numpy
Dynamic: license-file
